{"BTCUSDT":{"15m":{"symbol":"BTCUSDT","interval":"15m","price":66813.3,"rsi":24.24,"lower":66695,"upper":69190.4,"signal":"WAIT","lastSignal":"WAIT","time":1770794691280},"1h":{"symbol":"BTCUSDT","interval":"1h","price":66813.3,"rsi":29.28,"lower":66767.9,"upper":71014.2,"signal":"WAIT","lastSignal":"WAIT","time":1770794691281},"2h":{"symbol":"BTCUSDT","interval":"2h","price":66813.3,"rsi":36.39,"lower":67367.8,"upper":71472.6,"signal":"WAIT","lastSignal":"WAIT","time":1770794691283},"4h":{"symbol":"BTCUSDT","interval":"4h","price":66813.3,"rsi":41.37,"lower":62868.1,"upper":78749.9,"signal":"WAIT","lastSignal":"WAIT","time":1770794691284},"1d":{"symbol":"BTCUSDT","interval":"1d","price":66813.3,"rsi":32.36,"lower":62868.1,"upper":96907.9,"signal":"WAIT","lastSignal":"WAIT","time":1770794691285}},"ETHUSDT":{"15m":{"symbol":"ETHUSDT","interval":"15m","price":1948.76,"rsi":24.23,"lower":1944.59,"upper":2028.56,"signal":"WAIT","lastSignal":"WAIT","time":1770794691286,"entry":2002.1,"tp":1999.9999999999995,"sl":2003.15},"1h":{"symbol":"ETHUSDT","interval":"1h","price":1948.76,"rsi":28.04,"lower":1948.56,"upper":2130.56,"signal":"WAIT","lastSignal":"WAIT","time":1770794691287,"entry":2004.71,"tp":2002.0300000000002,"sl":2006.05},"2h":{"symbol":"ETHUSDT","interval":"2h","price":1948.76,"rsi":36.32,"lower":1973.31,"upper":2130.98,"signal":"WAIT","lastSignal":"WAIT","time":1770794691287},"4h":{"symbol":"ETHUSDT","interval":"4h","price":1948.76,"rsi":42.16,"lower":1824.95,"upper":2345.55,"signal":"WAIT","lastSignal":"WAIT","time":1770794691288},"1d":{"symbol":"ETHUSDT","interval":"1d","price":1948.76,"rsi":30.21,"lower":1824.95,"upper":3353.27,"signal":"WAIT","lastSignal":"WAIT","time":1770794691289}},"SOLUSDT":{"15m":{"symbol":"SOLUSDT","interval":"15m","price":80.58,"rsi":30.19,"lower":80.62,"upper":84.17,"signal":"WAIT","lastSignal":"WAIT","time":1770794691289,"entry":84.41,"tp":84.41,"sl":84.41},"1h":{"symbol":"SOLUSDT","interval":"1h","price":80.58,"rsi":29.69,"lower":80.81,"upper":87.9,"signal":"WAIT","lastSignal":"WAIT","time":1770794691290},"2h":{"symbol":"SOLUSDT","interval":"2h","price":80.58,"rsi":36.83,"lower":81.85,"upper":88.5,"signal":"WAIT","lastSignal":"WAIT","time":1770794691290},"4h":{"symbol":"SOLUSDT","interval":"4h","price":80.58,"rsi":40.22,"lower":76.66,"upper":104.62,"signal":"WAIT","lastSignal":"WAIT","time":1770794691291},"1d":{"symbol":"SOLUSDT","interval":"1d","price":80.58,"rsi":28.44,"lower":78.29,"upper":146.61,"signal":"WAIT","lastSignal":"WAIT","time":1770794691291}},"SUIUSDT":{"15m":{"symbol":"SUIUSDT","interval":"15m","price":0.89501149,"rsi":25.97,"lower":0.895,"upper":0.9347,"signal":"WAIT","lastSignal":"WAIT","time":1770794691292},"1h":{"symbol":"SUIUSDT","interval":"1h","price":0.89501149,"rsi":27.69,"lower":0.8948,"upper":0.9851,"signal":"WAIT","lastSignal":"WAIT","time":1770794691293},"2h":{"symbol":"SUIUSDT","interval":"2h","price":0.89501149,"rsi":32.17,"lower":0.9049,"upper":1.011,"signal":"WAIT","lastSignal":"WAIT","time":1770794691294},"4h":{"symbol":"SUIUSDT","interval":"4h","price":0.89501149,"rsi":37.27,"lower":0.8821,"upper":1.1534,"signal":"WAIT","lastSignal":"WAIT","time":1770794691295},"1d":{"symbol":"SUIUSDT","interval":"1d","price":0.89501149,"rsi":27.74,"lower":0.8821,"upper":1.9029,"signal":"WAIT","lastSignal":"WAIT","time":1770794691296}},"LINKUSDT":{"15m":{"symbol":"LINKUSDT","interval":"15m","price":8.31,"rsi":30.99,"lower":8.302,"upper":8.598,"signal":"WAIT","lastSignal":"WAIT","time":1770794691297},"1h":{"symbol":"LINKUSDT","interval":"1h","price":8.31,"rsi":28.3,"lower":8.302,"upper":8.964,"signal":"WAIT","lastSignal":"WAIT","time":1770794691298},"2h":{"symbol":"LINKUSDT","interval":"2h","price":8.31,"rsi":35,"lower":8.367,"upper":8.997,"signal":"WAIT","lastSignal":"WAIT","time":1770794691298},"4h":{"symbol":"LINKUSDT","interval":"4h","price":8.31,"rsi":42.37,"lower":7.906,"upper":9.801,"signal":"WAIT","lastSignal":"WAIT","time":1770794691299},"1d":{"symbol":"LINKUSDT","interval":"1d","price":8.31,"rsi":29.55,"lower":7.906,"upper":14.106,"signal":"WAIT","lastSignal":"WAIT","time":1770794691300}}}